csvTMFlow/__init__.py
csvTMFlow-0.0.1.dist-info/LICENSE.txt
csvTMFlow-0.0.1.dist-info/METADATA
csvTMFlow-0.0.1.dist-info/WHEEL
csvTMFlow-0.0.1.dist-info/top_level.txt
csvTMFlow-0.0.1.dist-info/RECORD
