Metadata-Version: 2.1
Name: csvTMFlow
Version: 0.0.1
Summary: Process Flow
Home-page: UNKNOWN
Author: Ritz
Author-email: UNKNOWN
License: UNKNOWN
Platform: UNKNOWN
Requires-Dist: xlrd
Requires-Dist: xlwt
Requires-Dist: xlutils
Requires-Dist: dbutils
